pycamhd/__init__.py
pycamhd/pycamhd.py
pycamhd-0.7.0.dist-info/DESCRIPTION.rst
pycamhd-0.7.0.dist-info/METADATA
pycamhd-0.7.0.dist-info/RECORD
pycamhd-0.7.0.dist-info/WHEEL
pycamhd-0.7.0.dist-info/metadata.json
pycamhd-0.7.0.dist-info/top_level.txt
